{
	"info": {
		"_postman_id": "fullego-backend-api",
		"name": "Fullego Backend API",
		"description": "Complete API collection for Fullego Wealth Management Platform",
		"schema": "https://schema.getpostman.com/json/collection/v2.1.0/collection.json"
	},
	"item": [
		{
			"name": "Authentication",
			"item": [
				{
					"name": "Register",
					"request": {
						"method": "POST",
						"header": [
							{
								"key": "Content-Type",
								"value": "application/json"
							}
						],
						"body": {
							"mode": "raw",
							"raw": "{\n    \"email\": \"user@example.com\",\n    \"password\": \"SecurePassword123!\",\n    \"first_name\": \"John\",\n    \"last_name\": \"Doe\",\n    \"phone\": \"+1234567890\"\n}",
							"options": {
								"raw": {
									"language": "json"
								}
							}
						},
						"url": {
							"raw": "{{base_url}}/api/v1/auth/register",
							"host": ["{{base_url}}"],
							"path": ["api", "v1", "auth", "register"]
						}
					},
					"response": []
				},
				{
					"name": "Login",
					"event": [
						{
							"listen": "test",
							"script": {
								"exec": [
									"if (pm.response.code === 200) {",
									"    var jsonData = pm.response.json();",
									"    pm.environment.set(\"access_token\", jsonData.access_token);",
									"}"
								],
								"type": "text/javascript"
							}
						}
					],
					"request": {
						"method": "POST",
						"header": [
							{
								"key": "Content-Type",
								"value": "application/json"
							}
						],
						"body": {
							"mode": "raw",
							"raw": "{\n    \"email\": \"user@example.com\",\n    \"password\": \"SecurePassword123!\"\n}",
							"options": {
								"raw": {
									"language": "json"
								}
							}
						},
						"url": {
							"raw": "{{base_url}}/api/v1/auth/login",
							"host": ["{{base_url}}"],
							"path": ["api", "v1", "auth", "login"]
						}
					},
					"response": []
				}
			]
		},
		{
			"name": "Users",
			"item": [
				{
					"name": "Get Current User",
					"request": {
						"method": "GET",
						"header": [
							{
								"key": "Authorization",
								"value": "Bearer {{access_token}}"
							}
						],
						"url": {
							"raw": "{{base_url}}/api/v1/users/me",
							"host": ["{{base_url}}"],
							"path": ["api", "v1", "users", "me"]
						}
					},
					"response": []
				},
				{
					"name": "Update User Profile",
					"request": {
						"method": "PUT",
						"header": [
							{
								"key": "Authorization",
								"value": "Bearer {{access_token}}"
							},
							{
								"key": "Content-Type",
								"value": "application/json"
							}
						],
						"body": {
							"mode": "raw",
							"raw": "{\n    \"first_name\": \"John Updated\",\n    \"last_name\": \"Doe Updated\",\n    \"phone\": \"+1234567891\"\n}",
							"options": {
								"raw": {
									"language": "json"
								}
							}
						},
						"url": {
							"raw": "{{base_url}}/api/v1/users/me",
							"host": ["{{base_url}}"],
							"path": ["api", "v1", "users", "me"]
						}
					},
					"response": []
				},
				{
					"name": "List Users (Admin)",
					"request": {
						"method": "GET",
						"header": [
							{
								"key": "Authorization",
								"value": "Bearer {{access_token}}"
							}
						],
						"url": {
							"raw": "{{base_url}}/api/v1/users?role=investor&search=john&page=1&page_size=20",
							"host": ["{{base_url}}"],
							"path": ["api", "v1", "users"],
							"query": [
								{
									"key": "role",
									"value": "investor"
								},
								{
									"key": "search",
									"value": "john"
								},
								{
									"key": "page",
									"value": "1"
								},
								{
									"key": "page_size",
									"value": "20"
								}
							]
						}
					},
					"response": []
				},
				{
					"name": "Get User by ID",
					"request": {
						"method": "GET",
						"header": [
							{
								"key": "Authorization",
								"value": "Bearer {{access_token}}"
							}
						],
						"url": {
							"raw": "{{base_url}}/api/v1/users/:user_id",
							"host": ["{{base_url}}"],
							"path": ["api", "v1", "users", ":user_id"],
							"variable": [
								{
									"key": "user_id",
									"value": ""
								}
							]
						}
					},
					"response": []
				},
				{
					"name": "Delete User (Admin)",
					"request": {
						"method": "DELETE",
						"header": [
							{
								"key": "Authorization",
								"value": "Bearer {{access_token}}"
							}
						],
						"url": {
							"raw": "{{base_url}}/api/v1/users/:user_id",
							"host": ["{{base_url}}"],
							"path": ["api", "v1", "users", ":user_id"],
							"variable": [
								{
									"key": "user_id",
									"value": ""
								}
							]
						}
					},
					"response": []
				},
				{
					"name": "Update User Role (Admin)",
					"request": {
						"method": "PUT",
						"header": [
							{
								"key": "Authorization",
								"value": "Bearer {{access_token}}"
							},
							{
								"key": "Content-Type",
								"value": "application/json"
							}
						],
						"body": {
							"mode": "raw",
							"raw": "{\n    \"new_role\": \"advisor\"\n}",
							"options": {
								"raw": {
									"language": "json"
								}
							}
						},
						"url": {
							"raw": "{{base_url}}/api/v1/users/:user_id/role",
							"host": ["{{base_url}}"],
							"path": ["api", "v1", "users", ":user_id", "role"],
							"variable": [
								{
									"key": "user_id",
									"value": ""
								}
							]
						}
					},
					"response": []
				},
				{
					"name": "Get User Statistics (Admin)",
					"request": {
						"method": "GET",
						"header": [
							{
								"key": "Authorization",
								"value": "Bearer {{access_token}}"
							}
						],
						"url": {
							"raw": "{{base_url}}/api/v1/users/stats/summary",
							"host": ["{{base_url}}"],
							"path": ["api", "v1", "users", "stats", "summary"]
						}
					},
					"response": []
				}
			]
		},
		{
			"name": "Accounts",
			"item": [
				{
					"name": "Create Account",
					"request": {
						"method": "POST",
						"header": [
							{
								"key": "Authorization",
								"value": "Bearer {{access_token}}"
							},
							{
								"key": "Content-Type",
								"value": "application/json"
							}
						],
						"body": {
							"mode": "raw",
							"raw": "{\n    \"account_type\": \"individual\",\n    \"account_name\": \"John Doe Account\",\n    \"is_joint\": false,\n    \"tax_id\": \"123-45-6789\"\n}",
							"options": {
								"raw": {
									"language": "json"
								}
							}
						},
						"url": {
							"raw": "{{base_url}}/api/v1/accounts",
							"host": ["{{base_url}}"],
							"path": ["api", "v1", "accounts"]
						}
					},
					"response": []
				},
				{
					"name": "Get Account",
					"request": {
						"method": "GET",
						"header": [
							{
								"key": "Authorization",
								"value": "Bearer {{access_token}}"
							}
						],
						"url": {
							"raw": "{{base_url}}/api/v1/accounts/me",
							"host": ["{{base_url}}"],
							"path": ["api", "v1", "accounts", "me"]
						}
					},
					"response": []
				},
				{
					"name": "Update Account",
					"request": {
						"method": "PUT",
						"header": [
							{
								"key": "Authorization",
								"value": "Bearer {{access_token}}"
							},
							{
								"key": "Content-Type",
								"value": "application/json"
							}
						],
						"body": {
							"mode": "raw",
							"raw": "{\n    \"account_name\": \"Updated Account Name\"\n}",
							"options": {
								"raw": {
									"language": "json"
								}
							}
						},
						"url": {
							"raw": "{{base_url}}/api/v1/accounts/me",
							"host": ["{{base_url}}"],
							"path": ["api", "v1", "accounts", "me"]
						}
					},
					"response": []
				}
			]
		},
		{
			"name": "Assets",
			"item": [
				{
					"name": "List Assets",
					"request": {
						"method": "GET",
						"header": [
							{
								"key": "Authorization",
								"value": "Bearer {{access_token}}"
							}
						],
						"url": {
							"raw": "{{base_url}}/api/v1/assets",
							"host": ["{{base_url}}"],
							"path": ["api", "v1", "assets"]
						}
					},
					"response": []
				},
				{
					"name": "Create Asset",
					"request": {
						"method": "POST",
						"header": [
							{
								"key": "Authorization",
								"value": "Bearer {{access_token}}"
							},
							{
								"key": "Content-Type",
								"value": "application/json"
							}
						],
						"body": {
							"mode": "raw",
							"raw": "{\n    \"asset_type\": \"stock\",\n    \"name\": \"Apple Inc.\",\n    \"symbol\": \"AAPL\",\n    \"description\": \"Technology stock\",\n    \"current_value\": 150.50,\n    \"currency\": \"USD\"\n}",
							"options": {
								"raw": {
									"language": "json"
								}
							}
						},
						"url": {
							"raw": "{{base_url}}/api/v1/assets",
							"host": ["{{base_url}}"],
							"path": ["api", "v1", "assets"]
						}
					},
					"response": []
				},
				{
					"name": "Get Asset",
					"request": {
						"method": "GET",
						"header": [
							{
								"key": "Authorization",
								"value": "Bearer {{access_token}}"
							}
						],
						"url": {
							"raw": "{{base_url}}/api/v1/assets/:asset_id",
							"host": ["{{base_url}}"],
							"path": ["api", "v1", "assets", ":asset_id"],
							"variable": [
								{
									"key": "asset_id",
									"value": ""
								}
							]
						}
					},
					"response": []
				},
				{
					"name": "Update Asset",
					"request": {
						"method": "PUT",
						"header": [
							{
								"key": "Authorization",
								"value": "Bearer {{access_token}}"
							},
							{
								"key": "Content-Type",
								"value": "application/json"
							}
						],
						"body": {
							"mode": "raw",
							"raw": "{\n    \"name\": \"Updated Asset Name\",\n    \"current_value\": 160.00\n}",
							"options": {
								"raw": {
									"language": "json"
								}
							}
						},
						"url": {
							"raw": "{{base_url}}/api/v1/assets/:asset_id",
							"host": ["{{base_url}}"],
							"path": ["api", "v1", "assets", ":asset_id"],
							"variable": [
								{
									"key": "asset_id",
									"value": ""
								}
							]
						}
					},
					"response": []
				},
				{
					"name": "Delete Asset",
					"request": {
						"method": "DELETE",
						"header": [
							{
								"key": "Authorization",
								"value": "Bearer {{access_token}}"
							}
						],
						"url": {
							"raw": "{{base_url}}/api/v1/assets/:asset_id",
							"host": ["{{base_url}}"],
							"path": ["api", "v1", "assets", ":asset_id"],
							"variable": [
								{
									"key": "asset_id",
									"value": ""
								}
							]
						}
					},
					"response": []
				}
			]
		},
		{
			"name": "Portfolio",
			"item": [
				{
					"name": "Get Portfolio",
					"request": {
						"method": "GET",
						"header": [
							{
								"key": "Authorization",
								"value": "Bearer {{access_token}}"
							}
						],
						"url": {
							"raw": "{{base_url}}/api/v1/portfolio",
							"host": ["{{base_url}}"],
							"path": ["api", "v1", "portfolio"]
						}
					},
					"response": []
				},
				{
					"name": "Get Portfolio Performance",
					"request": {
						"method": "GET",
						"header": [
							{
								"key": "Authorization",
								"value": "Bearer {{access_token}}"
							}
						],
						"url": {
							"raw": "{{base_url}}/api/v1/portfolio/performance",
							"host": ["{{base_url}}"],
							"path": ["api", "v1", "portfolio", "performance"]
						}
					},
					"response": []
				}
			]
		},
		{
			"name": "Trading",
			"item": [
				{
					"name": "Get Transactions",
					"request": {
						"method": "GET",
						"header": [
							{
								"key": "Authorization",
								"value": "Bearer {{access_token}}"
							}
						],
						"url": {
							"raw": "{{base_url}}/api/v1/trading/transactions?start_date=2024-01-01&end_date=2024-12-31&limit=100",
							"host": ["{{base_url}}"],
							"path": ["api", "v1", "trading", "transactions"],
							"query": [
								{
									"key": "start_date",
									"value": "2024-01-01",
									"description": "Start date (YYYY-MM-DD)"
								},
								{
									"key": "end_date",
									"value": "2024-12-31",
									"description": "End date (YYYY-MM-DD)"
								},
								{
									"key": "limit",
									"value": "100",
									"description": "Number of transactions"
								}
							]
						}
					},
					"response": []
				},
				{
					"name": "Get Assets",
					"request": {
						"method": "GET",
						"header": [
							{
								"key": "Authorization",
								"value": "Bearer {{access_token}}"
							}
						],
						"url": {
							"raw": "{{base_url}}/api/v1/trading/assets",
							"host": ["{{base_url}}"],
							"path": ["api", "v1", "trading", "assets"]
						}
					},
					"response": []
				},
				{
					"name": "Get Account",
					"request": {
						"method": "GET",
						"header": [
							{
								"key": "Authorization",
								"value": "Bearer {{access_token}}"
							}
						],
						"url": {
							"raw": "{{base_url}}/api/v1/trading/account",
							"host": ["{{base_url}}"],
							"path": ["api", "v1", "trading", "account"]
						}
					},
					"response": []
				},
				{
					"name": "Create Order (Placeholder)",
					"request": {
						"method": "POST",
						"header": [
							{
								"key": "Authorization",
								"value": "Bearer {{access_token}}"
							},
							{
								"key": "Content-Type",
								"value": "application/json"
							}
						],
						"body": {
							"mode": "raw",
							"raw": "{\n    \"order_type\": \"market\",\n    \"symbol\": \"AAPL\",\n    \"quantity\": 10,\n    \"side\": \"buy\"\n}",
							"options": {
								"raw": {
									"language": "json"
								}
							}
						},
						"url": {
							"raw": "{{base_url}}/api/v1/trading/orders",
							"host": ["{{base_url}}"],
							"path": ["api", "v1", "trading", "orders"]
						}
					},
					"response": []
				}
			]
		},
		{
			"name": "Marketplace",
			"item": [
				{
					"name": "List Listings",
					"request": {
						"method": "GET",
						"header": [
							{
								"key": "Authorization",
								"value": "Bearer {{access_token}}"
							}
						],
						"url": {
							"raw": "{{base_url}}/api/v1/marketplace/listings",
							"host": ["{{base_url}}"],
							"path": ["api", "v1", "marketplace", "listings"]
						}
					},
					"response": []
				},
				{
					"name": "Create Listing",
					"request": {
						"method": "POST",
						"header": [
							{
								"key": "Authorization",
								"value": "Bearer {{access_token}}"
							},
							{
								"key": "Content-Type",
								"value": "application/json"
							}
						],
						"body": {
							"mode": "raw",
							"raw": "{\n    \"asset_id\": \"\",\n    \"title\": \"Luxury Yacht for Sale\",\n    \"description\": \"Beautiful 50ft yacht\",\n    \"asking_price\": 500000,\n    \"currency\": \"USD\"\n}",
							"options": {
								"raw": {
									"language": "json"
								}
							}
						},
						"url": {
							"raw": "{{base_url}}/api/v1/marketplace/listings",
							"host": ["{{base_url}}"],
							"path": ["api", "v1", "marketplace", "listings"]
						}
					},
					"response": []
				},
				{
					"name": "Submit Offer",
					"request": {
						"method": "POST",
						"header": [
							{
								"key": "Authorization",
								"value": "Bearer {{access_token}}"
							},
							{
								"key": "Content-Type",
								"value": "application/json"
							}
						],
						"body": {
							"mode": "raw",
							"raw": "{\n    \"offer_amount\": 480000,\n    \"currency\": \"USD\",\n    \"message\": \"Interested in purchasing\"\n}",
							"options": {
								"raw": {
									"language": "json"
								}
							}
						},
						"url": {
							"raw": "{{base_url}}/api/v1/marketplace/listings/:listing_id/offers",
							"host": ["{{base_url}}"],
							"path": ["api", "v1", "marketplace", "listings", ":listing_id", "offers"],
							"variable": [
								{
									"key": "listing_id",
									"value": ""
								}
							]
						}
					},
					"response": []
				},
				{
					"name": "Get My Offers",
					"request": {
						"method": "GET",
						"header": [
							{
								"key": "Authorization",
								"value": "Bearer {{access_token}}"
							}
						],
						"url": {
							"raw": "{{base_url}}/api/v1/marketplace/offers",
							"host": ["{{base_url}}"],
							"path": ["api", "v1", "marketplace", "offers"]
						}
					},
					"response": []
				}
			]
		},
		{
			"name": "Payments",
			"item": [
				{
					"name": "Create Payment Intent",
					"request": {
						"method": "POST",
						"header": [
							{
								"key": "Authorization",
								"value": "Bearer {{access_token}}"
							},
							{
								"key": "Content-Type",
								"value": "application/json"
							}
						],
						"body": {
							"mode": "raw",
							"raw": "{\n    \"amount\": 10000,\n    \"currency\": \"usd\",\n    \"payment_method\": \"card\"\n}",
							"options": {
								"raw": {
									"language": "json"
								}
							}
						},
						"url": {
							"raw": "{{base_url}}/api/v1/payments/create-intent",
							"host": ["{{base_url}}"],
							"path": ["api", "v1", "payments", "create-intent"]
						}
					},
					"response": []
				},
				{
					"name": "Stripe Webhook",
					"request": {
						"method": "POST",
						"header": [
							{
								"key": "Content-Type",
								"value": "application/json"
							}
						],
						"body": {
							"mode": "raw",
							"raw": "{\n    \"type\": \"payment_intent.succeeded\",\n    \"data\": {\n        \"object\": {\n            \"id\": \"pi_1234567890\"\n        }\n    }\n}",
							"options": {
								"raw": {
									"language": "json"
								}
							}
						},
						"url": {
							"raw": "{{base_url}}/api/v1/payments/webhook",
							"host": ["{{base_url}}"],
							"path": ["api", "v1", "payments", "webhook"]
						}
					},
					"response": []
				}
			]
		},
		{
			"name": "Subscriptions",
			"item": [
				{
					"name": "Get Subscription",
					"request": {
						"method": "GET",
						"header": [
							{
								"key": "Authorization",
								"value": "Bearer {{access_token}}"
							}
						],
						"url": {
							"raw": "{{base_url}}/api/v1/subscriptions",
							"host": ["{{base_url}}"],
							"path": ["api", "v1", "subscriptions"]
						}
					},
					"response": []
				},
				{
					"name": "Create Subscription",
					"request": {
						"method": "POST",
						"header": [
							{
								"key": "Authorization",
								"value": "Bearer {{access_token}}"
							},
							{
								"key": "Content-Type",
								"value": "application/json"
							}
						],
						"body": {
							"mode": "raw",
							"raw": "{\n    \"plan\": \"monthly\",\n    \"discount_code\": \"EARLYBIRD\"\n}",
							"options": {
								"raw": {
									"language": "json"
								}
							}
						},
						"url": {
							"raw": "{{base_url}}/api/v1/subscriptions",
							"host": ["{{base_url}}"],
							"path": ["api", "v1", "subscriptions"]
						}
					},
					"response": []
				},
				{
					"name": "Cancel Subscription",
					"request": {
						"method": "POST",
						"header": [
							{
								"key": "Authorization",
								"value": "Bearer {{access_token}}"
							}
						],
						"url": {
							"raw": "{{base_url}}/api/v1/subscriptions/cancel",
							"host": ["{{base_url}}"],
							"path": ["api", "v1", "subscriptions", "cancel"]
						}
					},
					"response": []
				},
				{
					"name": "Renew Subscription",
					"request": {
						"method": "POST",
						"header": [
							{
								"key": "Authorization",
								"value": "Bearer {{access_token}}"
							}
						],
						"url": {
							"raw": "{{base_url}}/api/v1/subscriptions/renew",
							"host": ["{{base_url}}"],
							"path": ["api", "v1", "subscriptions", "renew"]
						}
					},
					"response": []
				},
				{
					"name": "Upgrade/Downgrade Subscription",
					"request": {
						"method": "PUT",
						"header": [
							{
								"key": "Authorization",
								"value": "Bearer {{access_token}}"
							},
							{
								"key": "Content-Type",
								"value": "application/json"
							}
						],
						"body": {
							"mode": "raw",
							"raw": "{\n    \"new_plan\": \"annual\"\n}",
							"options": {
								"raw": {
									"language": "json"
								}
							}
						},
						"url": {
							"raw": "{{base_url}}/api/v1/subscriptions/upgrade",
							"host": ["{{base_url}}"],
							"path": ["api", "v1", "subscriptions", "upgrade"]
						}
					},
					"response": []
				},
				{
					"name": "Get Subscription History",
					"request": {
						"method": "GET",
						"header": [
							{
								"key": "Authorization",
								"value": "Bearer {{access_token}}"
							}
						],
						"url": {
							"raw": "{{base_url}}/api/v1/subscriptions/history",
							"host": ["{{base_url}}"],
							"path": ["api", "v1", "subscriptions", "history"]
						}
					},
					"response": []
				}
			]
		},
		{
			"name": "Banking",
			"item": [
				{
					"name": "Create Link Token",
					"request": {
						"method": "POST",
						"header": [
							{
								"key": "Authorization",
								"value": "Bearer {{access_token}}"
							}
						],
						"url": {
							"raw": "{{base_url}}/api/v1/banking/link-token",
							"host": ["{{base_url}}"],
							"path": ["api", "v1", "banking", "link-token"]
						}
					},
					"response": []
				},
				{
					"name": "Link Account",
					"request": {
						"method": "POST",
						"header": [
							{
								"key": "Authorization",
								"value": "Bearer {{access_token}}"
							},
							{
								"key": "Content-Type",
								"value": "application/json"
							}
						],
						"body": {
							"mode": "raw",
							"raw": "{\n    \"public_token\": \"public-sandbox-xxx\"\n}",
							"options": {
								"raw": {
									"language": "json"
								}
							}
						},
						"url": {
							"raw": "{{base_url}}/api/v1/banking/link",
							"host": ["{{base_url}}"],
							"path": ["api", "v1", "banking", "link"]
						}
					},
					"response": []
				},
				{
					"name": "Get Linked Accounts",
					"request": {
						"method": "GET",
						"header": [
							{
								"key": "Authorization",
								"value": "Bearer {{access_token}}"
							}
						],
						"url": {
							"raw": "{{base_url}}/api/v1/banking/accounts",
							"host": ["{{base_url}}"],
							"path": ["api", "v1", "banking", "accounts"]
						}
					},
					"response": []
				},
				{
					"name": "Get Linked Account Details",
					"request": {
						"method": "GET",
						"header": [
							{
								"key": "Authorization",
								"value": "Bearer {{access_token}}"
							}
						],
						"url": {
							"raw": "{{base_url}}/api/v1/banking/accounts/:linked_account_id",
							"host": ["{{base_url}}"],
							"path": ["api", "v1", "banking", "accounts", ":linked_account_id"],
							"variable": [
								{
									"key": "linked_account_id",
									"value": ""
								}
							]
						}
					},
					"response": []
				},
				{
					"name": "Sync Transactions",
					"request": {
						"method": "POST",
						"header": [
							{
								"key": "Authorization",
								"value": "Bearer {{access_token}}"
							}
						],
						"url": {
							"raw": "{{base_url}}/api/v1/banking/sync/:linked_account_id",
							"host": ["{{base_url}}"],
							"path": ["api", "v1", "banking", "sync", ":linked_account_id"],
							"variable": [
								{
									"key": "linked_account_id",
									"value": ""
								}
							]
						}
					},
					"response": []
				},
				{
					"name": "Refresh Account Balance",
					"request": {
						"method": "POST",
						"header": [
							{
								"key": "Authorization",
								"value": "Bearer {{access_token}}"
							}
						],
						"url": {
							"raw": "{{base_url}}/api/v1/banking/accounts/:linked_account_id/refresh",
							"host": ["{{base_url}}"],
							"path": ["api", "v1", "banking", "accounts", ":linked_account_id", "refresh"],
							"variable": [
								{
									"key": "linked_account_id",
									"value": ""
								}
							]
						}
					},
					"response": []
				},
				{
					"name": "Get Account Transactions",
					"request": {
						"method": "GET",
						"header": [
							{
								"key": "Authorization",
								"value": "Bearer {{access_token}}"
							}
						],
						"url": {
							"raw": "{{base_url}}/api/v1/banking/accounts/:linked_account_id/transactions?start_date=2024-01-01&end_date=2024-12-31&limit=50",
							"host": ["{{base_url}}"],
							"path": ["api", "v1", "banking", "accounts", ":linked_account_id", "transactions"],
							"query": [
								{
									"key": "start_date",
									"value": "2024-01-01"
								},
								{
									"key": "end_date",
									"value": "2024-12-31"
								},
								{
									"key": "limit",
									"value": "50"
								}
							],
							"variable": [
								{
									"key": "linked_account_id",
									"value": ""
								}
							]
						}
					},
					"response": []
				},
				{
					"name": "Disconnect Account",
					"request": {
						"method": "DELETE",
						"header": [
							{
								"key": "Authorization",
								"value": "Bearer {{access_token}}"
							}
						],
						"url": {
							"raw": "{{base_url}}/api/v1/banking/accounts/:linked_account_id",
							"host": ["{{base_url}}"],
							"path": ["api", "v1", "banking", "accounts", ":linked_account_id"],
							"variable": [
								{
									"key": "linked_account_id",
									"value": ""
								}
							]
						}
					},
					"response": []
				}
			]
		},
		{
			"name": "Documents",
			"item": [
				{
					"name": "Upload Document",
					"request": {
						"method": "POST",
						"header": [
							{
								"key": "Authorization",
								"value": "Bearer {{access_token}}"
							}
						],
						"body": {
							"mode": "formdata",
							"formdata": [
								{
									"key": "file",
									"type": "file",
									"src": []
								},
								{
									"key": "document_type",
									"value": "kyc_document",
									"type": "text"
								},
								{
									"key": "description",
									"value": "KYC verification document",
									"type": "text"
								}
							]
						},
						"url": {
							"raw": "{{base_url}}/api/v1/documents/upload",
							"host": ["{{base_url}}"],
							"path": ["api", "v1", "documents", "upload"]
						}
					},
					"response": []
				},
				{
					"name": "List Documents",
					"request": {
						"method": "GET",
						"header": [
							{
								"key": "Authorization",
								"value": "Bearer {{access_token}}"
							}
						],
						"url": {
							"raw": "{{base_url}}/api/v1/documents",
							"host": ["{{base_url}}"],
							"path": ["api", "v1", "documents"]
						}
					},
					"response": []
				},
				{
					"name": "Get Document",
					"request": {
						"method": "GET",
						"header": [
							{
								"key": "Authorization",
								"value": "Bearer {{access_token}}"
							}
						],
						"url": {
							"raw": "{{base_url}}/api/v1/documents/:document_id",
							"host": ["{{base_url}}"],
							"path": ["api", "v1", "documents", ":document_id"],
							"variable": [
								{
									"key": "document_id",
									"value": ""
								}
							]
						}
					},
					"response": []
				},
				{
					"name": "Download Document",
					"request": {
						"method": "GET",
						"header": [
							{
								"key": "Authorization",
								"value": "Bearer {{access_token}}"
							}
						],
						"url": {
							"raw": "{{base_url}}/api/v1/documents/:document_id/download",
							"host": ["{{base_url}}"],
							"path": ["api", "v1", "documents", ":document_id", "download"],
							"variable": [
								{
									"key": "document_id",
									"value": ""
								}
							]
						}
					},
					"response": []
				},
				{
					"name": "Update Document",
					"request": {
						"method": "PUT",
						"header": [
							{
								"key": "Authorization",
								"value": "Bearer {{access_token}}"
							},
							{
								"key": "Content-Type",
								"value": "application/json"
							}
						],
						"body": {
							"mode": "raw",
							"raw": "{\n    \"description\": \"Updated description\",\n    \"document_type\": \"kyc_document\"\n}",
							"options": {
								"raw": {
									"language": "json"
								}
							}
						},
						"url": {
							"raw": "{{base_url}}/api/v1/documents/:document_id",
							"host": ["{{base_url}}"],
							"path": ["api", "v1", "documents", ":document_id"],
							"variable": [
								{
									"key": "document_id",
									"value": ""
								}
							]
						}
					},
					"response": []
				},
				{
					"name": "Delete Document",
					"request": {
						"method": "DELETE",
						"header": [
							{
								"key": "Authorization",
								"value": "Bearer {{access_token}}"
							}
						],
						"url": {
							"raw": "{{base_url}}/api/v1/documents/:document_id",
							"host": ["{{base_url}}"],
							"path": ["api", "v1", "documents", ":document_id"],
							"variable": [
								{
									"key": "document_id",
									"value": ""
								}
							]
						}
					},
					"response": []
				},
				{
					"name": "Get Document Statistics",
					"request": {
						"method": "GET",
						"header": [
							{
								"key": "Authorization",
								"value": "Bearer {{access_token}}"
							}
						],
						"url": {
							"raw": "{{base_url}}/api/v1/documents/stats/summary",
							"host": ["{{base_url}}"],
							"path": ["api", "v1", "documents", "stats", "summary"]
						}
					},
					"response": []
				}
			]
		},
		{
			"name": "Support",
			"item": [
				{
					"name": "Create Ticket",
					"request": {
						"method": "POST",
						"header": [
							{
								"key": "Authorization",
								"value": "Bearer {{access_token}}"
							},
							{
								"key": "Content-Type",
								"value": "application/json"
							}
						],
						"body": {
							"mode": "raw",
							"raw": "{\n    \"subject\": \"Account Issue\",\n    \"description\": \"Need help with my account\",\n    \"priority\": \"medium\"\n}",
							"options": {
								"raw": {
									"language": "json"
								}
							}
						},
						"url": {
							"raw": "{{base_url}}/api/v1/support/tickets",
							"host": ["{{base_url}}"],
							"path": ["api", "v1", "support", "tickets"]
						}
					},
					"response": []
				},
				{
					"name": "List Tickets",
					"request": {
						"method": "GET",
						"header": [
							{
								"key": "Authorization",
								"value": "Bearer {{access_token}}"
							}
						],
						"url": {
							"raw": "{{base_url}}/api/v1/support/tickets",
							"host": ["{{base_url}}"],
							"path": ["api", "v1", "support", "tickets"]
						}
					},
					"response": []
				},
				{
					"name": "Get Ticket",
					"request": {
						"method": "GET",
						"header": [
							{
								"key": "Authorization",
								"value": "Bearer {{access_token}}"
							}
						],
						"url": {
							"raw": "{{base_url}}/api/v1/support/tickets/:ticket_id",
							"host": ["{{base_url}}"],
							"path": ["api", "v1", "support", "tickets", ":ticket_id"],
							"variable": [
								{
									"key": "ticket_id",
									"value": ""
								}
							]
						}
					},
					"response": []
				},
				{
					"name": "Update Ticket",
					"request": {
						"method": "PUT",
						"header": [
							{
								"key": "Authorization",
								"value": "Bearer {{access_token}}"
							},
							{
								"key": "Content-Type",
								"value": "application/json"
							}
						],
						"body": {
							"mode": "raw",
							"raw": "{\n    \"status\": \"resolved\",\n    \"priority\": \"high\"\n}",
							"options": {
								"raw": {
									"language": "json"
								}
							}
						},
						"url": {
							"raw": "{{base_url}}/api/v1/support/tickets/:ticket_id?status=resolved&priority=high",
							"host": ["{{base_url}}"],
							"path": ["api", "v1", "support", "tickets", ":ticket_id"],
							"query": [
								{
									"key": "status",
									"value": "resolved"
								},
								{
									"key": "priority",
									"value": "high"
								}
							],
							"variable": [
								{
									"key": "ticket_id",
									"value": ""
								}
							]
						}
					},
					"response": []
				},
				{
					"name": "Add Ticket Reply",
					"request": {
						"method": "POST",
						"header": [
							{
								"key": "Authorization",
								"value": "Bearer {{access_token}}"
							},
							{
								"key": "Content-Type",
								"value": "application/json"
							}
						],
						"body": {
							"mode": "raw",
							"raw": "{\n    \"message\": \"Thank you for your response\",\n    \"is_internal\": false\n}",
							"options": {
								"raw": {
									"language": "json"
								}
							}
						},
						"url": {
							"raw": "{{base_url}}/api/v1/support/tickets/:ticket_id/replies",
							"host": ["{{base_url}}"],
							"path": ["api", "v1", "support", "tickets", ":ticket_id", "replies"],
							"variable": [
								{
									"key": "ticket_id",
									"value": ""
								}
							]
						}
					},
					"response": []
				},
				{
					"name": "Get Ticket Replies",
					"request": {
						"method": "GET",
						"header": [
							{
								"key": "Authorization",
								"value": "Bearer {{access_token}}"
							}
						],
						"url": {
							"raw": "{{base_url}}/api/v1/support/tickets/:ticket_id/replies?include_internal=false",
							"host": ["{{base_url}}"],
							"path": ["api", "v1", "support", "tickets", ":ticket_id", "replies"],
							"query": [
								{
									"key": "include_internal",
									"value": "false"
								}
							],
							"variable": [
								{
									"key": "ticket_id",
									"value": ""
								}
							]
						}
					},
					"response": []
				},
				{
					"name": "Get Support Statistics",
					"request": {
						"method": "GET",
						"header": [
							{
								"key": "Authorization",
								"value": "Bearer {{access_token}}"
							}
						],
						"url": {
							"raw": "{{base_url}}/api/v1/support/tickets/stats",
							"host": ["{{base_url}}"],
							"path": ["api", "v1", "support", "tickets", "stats"]
						}
					},
					"response": []
				}
			]
		},
		{
			"name": "Notifications",
			"item": [
				{
					"name": "Get Notifications",
					"request": {
						"method": "GET",
						"header": [
							{
								"key": "Authorization",
								"value": "Bearer {{access_token}}"
							}
						],
						"url": {
							"raw": "{{base_url}}/api/v1/notifications?unread_only=false",
							"host": ["{{base_url}}"],
							"path": ["api", "v1", "notifications"],
							"query": [
								{
									"key": "unread_only",
									"value": "false"
								}
							]
						}
					},
					"response": []
				},
				{
					"name": "Create Notification",
					"request": {
						"method": "POST",
						"header": [
							{
								"key": "Authorization",
								"value": "Bearer {{access_token}}"
							},
							{
								"key": "Content-Type",
								"value": "application/json"
							}
						],
						"body": {
							"mode": "raw",
							"raw": "{\n    \"account_id\": \"\",\n    \"notification_type\": \"general\",\n    \"title\": \"Welcome to Fullego\",\n    \"message\": \"Thank you for joining!\"\n}",
							"options": {
								"raw": {
									"language": "json"
								}
							}
						},
						"url": {
							"raw": "{{base_url}}/api/v1/notifications",
							"host": ["{{base_url}}"],
							"path": ["api", "v1", "notifications"]
						}
					},
					"response": []
				},
				{
					"name": "Mark Notification as Read",
					"request": {
						"method": "POST",
						"header": [
							{
								"key": "Authorization",
								"value": "Bearer {{access_token}}"
							}
						],
						"url": {
							"raw": "{{base_url}}/api/v1/notifications/:notification_id/read",
							"host": ["{{base_url}}"],
							"path": ["api", "v1", "notifications", ":notification_id", "read"],
							"variable": [
								{
									"key": "notification_id",
									"value": ""
								}
							]
						}
					},
					"response": []
				},
				{
					"name": "Mark All as Read",
					"request": {
						"method": "POST",
						"header": [
							{
								"key": "Authorization",
								"value": "Bearer {{access_token}}"
							}
						],
						"url": {
							"raw": "{{base_url}}/api/v1/notifications/read-all",
							"host": ["{{base_url}}"],
							"path": ["api", "v1", "notifications", "read-all"]
						}
					},
					"response": []
				},
				{
					"name": "Get Unread Count",
					"request": {
						"method": "GET",
						"header": [
							{
								"key": "Authorization",
								"value": "Bearer {{access_token}}"
							}
						],
						"url": {
							"raw": "{{base_url}}/api/v1/notifications/unread-count",
							"host": ["{{base_url}}"],
							"path": ["api", "v1", "notifications", "unread-count"]
						}
					},
					"response": []
				},
				{
					"name": "Delete Notification",
					"request": {
						"method": "DELETE",
						"header": [
							{
								"key": "Authorization",
								"value": "Bearer {{access_token}}"
							}
						],
						"url": {
							"raw": "{{base_url}}/api/v1/notifications/:notification_id",
							"host": ["{{base_url}}"],
							"path": ["api", "v1", "notifications", ":notification_id"],
							"variable": [
								{
									"key": "notification_id",
									"value": ""
								}
							]
						}
					},
					"response": []
				},
				{
					"name": "Delete All Notifications",
					"request": {
						"method": "DELETE",
						"header": [
							{
								"key": "Authorization",
								"value": "Bearer {{access_token}}"
							}
						],
						"url": {
							"raw": "{{base_url}}/api/v1/notifications?read_only=false",
							"host": ["{{base_url}}"],
							"path": ["api", "v1", "notifications"],
							"query": [
								{
									"key": "read_only",
									"value": "false"
								}
							]
						}
					},
					"response": []
				}
			]
		},
		{
			"name": "Reports",
			"item": [
				{
					"name": "Generate Portfolio Report",
					"request": {
						"method": "GET",
						"header": [
							{
								"key": "Authorization",
								"value": "Bearer {{access_token}}"
							}
						],
						"url": {
							"raw": "{{base_url}}/api/v1/reports/portfolio",
							"host": ["{{base_url}}"],
							"path": ["api", "v1", "reports", "portfolio"]
						}
					},
					"response": []
				},
				{
					"name": "Generate Performance Report",
					"request": {
						"method": "GET",
						"header": [
							{
								"key": "Authorization",
								"value": "Bearer {{access_token}}"
							}
						],
						"url": {
							"raw": "{{base_url}}/api/v1/reports/performance?days=30",
							"host": ["{{base_url}}"],
							"path": ["api", "v1", "reports", "performance"],
							"query": [
								{
									"key": "days",
									"value": "30",
									"description": "Number of days for performance period"
								}
							]
						}
					},
					"response": []
				},
				{
					"name": "Generate Transaction Report",
					"request": {
						"method": "GET",
						"header": [
							{
								"key": "Authorization",
								"value": "Bearer {{access_token}}"
							}
						],
						"url": {
							"raw": "{{base_url}}/api/v1/reports/transactions?start_date=2024-01-01&end_date=2024-12-31",
							"host": ["{{base_url}}"],
							"path": ["api", "v1", "reports", "transactions"],
							"query": [
								{
									"key": "start_date",
									"value": "2024-01-01"
								},
								{
									"key": "end_date",
									"value": "2024-12-31"
								}
							]
						}
					},
					"response": []
				}
			]
		},
		{
			"name": "Analytics",
			"item": [
				{
					"name": "Identify User",
					"request": {
						"method": "POST",
						"header": [
							{
								"key": "Authorization",
								"value": "Bearer {{access_token}}"
							},
							{
								"key": "Content-Type",
								"value": "application/json"
							}
						],
						"body": {
							"mode": "raw",
							"raw": "{\n    \"properties\": {\n        \"plan\": \"premium\",\n        \"signup_date\": \"2024-01-01\"\n    }\n}",
							"options": {
								"raw": {
									"language": "json"
								}
							}
						},
						"url": {
							"raw": "{{base_url}}/api/v1/analytics/identify",
							"host": ["{{base_url}}"],
							"path": ["api", "v1", "analytics", "identify"]
						}
					},
					"response": []
				},
				{
					"name": "Track Event",
					"request": {
						"method": "POST",
						"header": [
							{
								"key": "Authorization",
								"value": "Bearer {{access_token}}"
							},
							{
								"key": "Content-Type",
								"value": "application/json"
							}
						],
						"body": {
							"mode": "raw",
							"raw": "{\n    \"event\": \"asset_created\",\n    \"properties\": {\n        \"asset_type\": \"stock\",\n        \"value\": 1000\n    }\n}",
							"options": {
								"raw": {
									"language": "json"
								}
							}
						},
						"url": {
							"raw": "{{base_url}}/api/v1/analytics/track",
							"host": ["{{base_url}}"],
							"path": ["api", "v1", "analytics", "track"]
						}
					},
					"response": []
				},
				{
					"name": "Track Events Batch",
					"request": {
						"method": "POST",
						"header": [
							{
								"key": "Authorization",
								"value": "Bearer {{access_token}}"
							},
							{
								"key": "Content-Type",
								"value": "application/json"
							}
						],
						"body": {
							"mode": "raw",
							"raw": "{\n    \"events\": [\n        {\n            \"event\": \"page_viewed\",\n            \"properties\": {\"page\": \"dashboard\"}\n        },\n        {\n            \"event\": \"button_clicked\",\n            \"properties\": {\"button\": \"create_asset\"}\n        }\n    ]\n}",
							"options": {
								"raw": {
									"language": "json"
								}
							}
						},
						"url": {
							"raw": "{{base_url}}/api/v1/analytics/track-batch",
							"host": ["{{base_url}}"],
							"path": ["api", "v1", "analytics", "track-batch"]
						}
					},
					"response": []
				},
				{
					"name": "Track Page View",
					"request": {
						"method": "POST",
						"header": [
							{
								"key": "Authorization",
								"value": "Bearer {{access_token}}"
							},
							{
								"key": "Content-Type",
								"value": "application/json"
							}
						],
						"body": {
							"mode": "raw",
							"raw": "{\n    \"page_name\": \"Portfolio Dashboard\",\n    \"page_url\": \"/portfolio\",\n    \"properties\": {\n        \"section\": \"overview\"\n    }\n}",
							"options": {
								"raw": {
									"language": "json"
								}
							}
						},
						"url": {
							"raw": "{{base_url}}/api/v1/analytics/page-view",
							"host": ["{{base_url}}"],
							"path": ["api", "v1", "analytics", "page-view"]
						}
					},
					"response": []
				},
				{
					"name": "Get Analytics Dashboard",
					"request": {
						"method": "GET",
						"header": [
							{
								"key": "Authorization",
								"value": "Bearer {{access_token}}"
							}
						],
						"url": {
							"raw": "{{base_url}}/api/v1/analytics/dashboard",
							"host": ["{{base_url}}"],
							"path": ["api", "v1", "analytics", "dashboard"]
						}
					},
					"response": []
				}
			]
		},
		{
			"name": "Chat",
			"item": [
				{
					"name": "Create Sendbird User",
					"request": {
						"method": "POST",
						"header": [
							{
								"key": "Authorization",
								"value": "Bearer {{access_token}}"
							}
						],
						"url": {
							"raw": "{{base_url}}/api/v1/chat/users",
							"host": ["{{base_url}}"],
							"path": ["api", "v1", "chat", "users"]
						}
					},
					"response": []
				},
				{
					"name": "Create Channel",
					"request": {
						"method": "POST",
						"header": [
							{
								"key": "Authorization",
								"value": "Bearer {{access_token}}"
							},
							{
								"key": "Content-Type",
								"value": "application/json"
							}
						],
						"body": {
							"mode": "raw",
							"raw": "{\n    \"channel_url\": \"channel_123\",\n    \"user_ids\": [\"user_id_1\", \"user_id_2\"],\n    \"name\": \"My Channel\"\n}",
							"options": {
								"raw": {
									"language": "json"
								}
							}
						},
						"url": {
							"raw": "{{base_url}}/api/v1/chat/channels",
							"host": ["{{base_url}}"],
							"path": ["api", "v1", "chat", "channels"]
						}
					},
					"response": []
				},
				{
					"name": "Get Channels",
					"request": {
						"method": "GET",
						"header": [
							{
								"key": "Authorization",
								"value": "Bearer {{access_token}}"
							}
						],
						"url": {
							"raw": "{{base_url}}/api/v1/chat/channels?limit=20",
							"host": ["{{base_url}}"],
							"path": ["api", "v1", "chat", "channels"],
							"query": [
								{
									"key": "limit",
									"value": "20"
								}
							]
						}
					},
					"response": []
				},
				{
					"name": "Get Channel Details",
					"request": {
						"method": "GET",
						"header": [
							{
								"key": "Authorization",
								"value": "Bearer {{access_token}}"
							}
						],
						"url": {
							"raw": "{{base_url}}/api/v1/chat/channels/:channel_url",
							"host": ["{{base_url}}"],
							"path": ["api", "v1", "chat", "channels", ":channel_url"],
							"variable": [
								{
									"key": "channel_url",
									"value": ""
								}
							]
						}
					},
					"response": []
				},
				{
					"name": "Update Channel",
					"request": {
						"method": "PUT",
						"header": [
							{
								"key": "Authorization",
								"value": "Bearer {{access_token}}"
							},
							{
								"key": "Content-Type",
								"value": "application/json"
							}
						],
						"body": {
							"mode": "raw",
							"raw": "{\n    \"name\": \"Updated Channel Name\",\n    \"cover_url\": \"https://example.com/cover.jpg\"\n}",
							"options": {
								"raw": {
									"language": "json"
								}
							}
						},
						"url": {
							"raw": "{{base_url}}/api/v1/chat/channels/:channel_url",
							"host": ["{{base_url}}"],
							"path": ["api", "v1", "chat", "channels", ":channel_url"],
							"variable": [
								{
									"key": "channel_url",
									"value": ""
								}
							]
						}
					},
					"response": []
				},
				{
					"name": "Delete Channel",
					"request": {
						"method": "DELETE",
						"header": [
							{
								"key": "Authorization",
								"value": "Bearer {{access_token}}"
							}
						],
						"url": {
							"raw": "{{base_url}}/api/v1/chat/channels/:channel_url",
							"host": ["{{base_url}}"],
							"path": ["api", "v1", "chat", "channels", ":channel_url"],
							"variable": [
								{
									"key": "channel_url",
									"value": ""
								}
							]
						}
					},
					"response": []
				},
				{
					"name": "Send Message",
					"request": {
						"method": "POST",
						"header": [
							{
								"key": "Authorization",
								"value": "Bearer {{access_token}}"
							},
							{
								"key": "Content-Type",
								"value": "application/json"
							}
						],
						"body": {
							"mode": "raw",
							"raw": "{\n    \"channel_url\": \"channel_123\",\n    \"message\": \"Hello, this is a test message\"\n}",
							"options": {
								"raw": {
									"language": "json"
								}
							}
						},
						"url": {
							"raw": "{{base_url}}/api/v1/chat/messages",
							"host": ["{{base_url}}"],
							"path": ["api", "v1", "chat", "messages"]
						}
					},
					"response": []
				},
				{
					"name": "Get Messages",
					"request": {
						"method": "GET",
						"header": [
							{
								"key": "Authorization",
								"value": "Bearer {{access_token}}"
							}
						],
						"url": {
							"raw": "{{base_url}}/api/v1/chat/channels/:channel_url/messages?limit=50",
							"host": ["{{base_url}}"],
							"path": ["api", "v1", "chat", "channels", ":channel_url", "messages"],
							"query": [
								{
									"key": "limit",
									"value": "50"
								},
								{
									"key": "token",
									"value": "",
									"description": "Pagination token (optional)"
								}
							],
							"variable": [
								{
									"key": "channel_url",
									"value": ""
								}
							]
						}
					},
					"response": []
				}
			]
		},
		{
			"name": "KYC",
			"item": [
				{
					"name": "Start KYC",
					"request": {
						"method": "POST",
						"header": [
							{
								"key": "Authorization",
								"value": "Bearer {{access_token}}"
							}
						],
						"url": {
							"raw": "{{base_url}}/api/v1/kyc/start",
							"host": ["{{base_url}}"],
							"path": ["api", "v1", "kyc", "start"]
						}
					},
					"response": []
				},
				{
					"name": "Get KYC Status",
					"request": {
						"method": "GET",
						"header": [
							{
								"key": "Authorization",
								"value": "Bearer {{access_token}}"
							}
						],
						"url": {
							"raw": "{{base_url}}/api/v1/kyc/status",
							"host": ["{{base_url}}"],
							"path": ["api", "v1", "kyc", "status"]
						}
					},
					"response": []
				}
			]
		}
	],
	"variable": [
		{
			"key": "base_url",
			"value": "http://localhost:8000",
			"type": "string"
		},
		{
			"key": "access_token",
			"value": "",
			"type": "string"
		}
	]
}

